openerz_api/__init__.py
openerz_api/main.py
openerz_api-0.2.0.dist-info/LICENSE
openerz_api-0.2.0.dist-info/METADATA
openerz_api-0.2.0.dist-info/WHEEL
openerz_api-0.2.0.dist-info/top_level.txt
openerz_api-0.2.0.dist-info/RECORD
