Metadata-Version: 2.1
Name: openerz-api
Version: 0.2.0
Summary: A Python wrapper around the OpenERZ API.
Home-page: https://github.com/misialq/openerz-api
Author: Michał Ziemski
Author-email: michal@terrestryal.com
Classifier: Programming Language :: Python :: 3
Classifier: License :: OSI Approved :: MIT License
Classifier: Operating System :: OS Independent
Requires-Python: >=3.6
License-File: LICENSE
Requires-Dist: requests
